Bruni/Pstd.py
Bruni/__init__.py
Bruni-0.0.8.dist-info/LICENSE.txt
Bruni-0.0.8.dist-info/METADATA
Bruni-0.0.8.dist-info/WHEEL
Bruni-0.0.8.dist-info/top_level.txt
Bruni-0.0.8.dist-info/RECORD
