Metadata-Version: 2.1
Name: Bruni
Version: 0.0.8
Summary: Portfolio Analysis
Home-page: UNKNOWN
Author: Federico Bruni
Author-email: brunifederico99@gmail.com
License: UNKNOWN
Keywords: python,portfolio,standard deviation,std,stocks,Bruni,Montecarlo simulation
Platform: UNKNOWN
Classifier: Development Status :: 5 - Production/Stable
Classifier: Intended Audience :: Education
Classifier: Programming Language :: Python :: 3.9
Classifier: Operating System :: Microsoft :: Windows :: Windows 10
Classifier: Operating System :: MacOS :: MacOS X
License-File: LICENSE.txt
Requires-Dist: pandas
Requires-Dist: pandas-datareader
Requires-Dist: numpy
Requires-Dist: datetime
Requires-Dist: tqdm
